pycfloader/__init__.py
pycfloader/pycfloader.cp310-win_amd64.pyd
pycfloader/pycfloader.cp311-win_amd64.pyd
pycfloader/pycfloader.cp312-win_amd64.pyd
pycfloader/pycfloader.cp313-win_amd64.pyd
pycfloader/pycfloader.cp36-win_amd64.pyd
pycfloader/pycfloader.cp37-win_amd64.pyd
pycfloader/pycfloader.cp38-win_amd64.pyd
pycfloader/pycfloader.cp39-win_amd64.pyd
pycfloader/pycfloader.cpython-310-aarch64-linux-gnu.so
pycfloader/pycfloader.cpython-310-x86_64-linux-gnu.so
pycfloader/pycfloader.cpython-311-aarch64-linux-gnu.so
pycfloader/pycfloader.cpython-311-x86_64-linux-gnu.so
pycfloader/pycfloader.cpython-312-aarch64-linux-gnu.so
pycfloader/pycfloader.cpython-312-x86_64-linux-gnu.so
pycfloader/pycfloader.cpython-313-aarch64-linux-gnu.so
pycfloader/pycfloader.cpython-313-x86_64-linux-gnu.so
pycfloader/pycfloader.cpython-35m-aarch64-linux-gnu.so
pycfloader/pycfloader.cpython-35m-x86_64-linux-gnu.so
pycfloader/pycfloader.cpython-36m-aarch64-linux-gnu.so
pycfloader/pycfloader.cpython-36m-x86_64-linux-gnu.so
pycfloader/pycfloader.cpython-37m-aarch64-linux-gnu.so
pycfloader/pycfloader.cpython-37m-x86_64-linux-gnu.so
pycfloader/pycfloader.cpython-38-aarch64-linux-gnu.so
pycfloader/pycfloader.cpython-38-x86_64-linux-gnu.so
pycfloader/pycfloader.cpython-39-aarch64-linux-gnu.so
pycfloader/pycfloader.cpython-39-x86_64-linux-gnu.so
pycfloader-1.1.0.7.dist-info/LICENSE.txt
pycfloader-1.1.0.7.dist-info/METADATA
pycfloader-1.1.0.7.dist-info/WHEEL
pycfloader-1.1.0.7.dist-info/top_level.txt
pycfloader-1.1.0.7.dist-info/RECORD
