Metadata-Version: 2.1
Name: pycfloader
Version: 1.1.0.7
Summary: Encoder for python source code, to protect python your source code
Home-page: https://www.khcloud.net
Author: CFSoft Co. Ltd. 
Author-email: wdmsyf@sina.com
Maintainer: CFSoft CO.,LTD
Maintainer-email: wdmsyf@sina.com
License: UNKNOWN
Keywords: encoder protect source code development encryption protection accelerate
Platform: UNKNOWN
Classifier: Development Status :: 5 - Production/Stable
Classifier: Intended Audience :: Developers
Classifier: Topic :: Software Development :: Build Tools
Classifier: License :: OSI Approved :: MIT License
Classifier: Programming Language :: Python :: 3
Classifier: Programming Language :: Python :: 3.5
Classifier: Programming Language :: Python :: 3.6
Classifier: Programming Language :: Python :: 3.7
Classifier: Programming Language :: Python :: 3.8
Classifier: Programming Language :: Python :: 3.9
Classifier: Programming Language :: Python :: 3.10
Classifier: Programming Language :: Python :: 3.11
Classifier: Programming Language :: Python :: 3.12
Classifier: Programming Language :: Python :: 3.13
Requires-Python: >=3.5
